nanim/__init__.py
nanim/command_line.py
nanim/nanim.py
nanim/utility.py
nanim-0.0.3.dist-info/LICENSE
nanim-0.0.3.dist-info/METADATA
nanim-0.0.3.dist-info/WHEEL
nanim-0.0.3.dist-info/entry_points.txt
nanim-0.0.3.dist-info/top_level.txt
nanim-0.0.3.dist-info/RECORD
