Metadata-Version: 2.1
Name: nanim
Version: 0.0.3
Summary: A python animation library
Home-page: https://github.com/shahanneda/nanim
Author: Shahan Neda
Author-email: shahan.neda@gmail.com
License: UNKNOWN
Platform: UNKNOWN
Classifier: Programming Language :: Python :: 3
Classifier: License :: OSI Approved :: MIT License
Classifier: Operating System :: OS Independent
Requires-Python: >=3.6
Requires-Dist: ffmpeg
Requires-Dist: pycairo
